{
  "$schema": "https://mintlify.com/schema.json",
  "name": "Starter Kit",
  "variables": {
    "projectName": "My Awesome Project",
    "version": "1.2.3"
  },
  "logo": {
    "dark": "https://fliqr.ai/cdn/shop/files/Fliqr_9.png?v=1712643720&width=500",
    "light": "https://fliqr.ai/cdn/shop/files/Fliqr_9.png?v=1712643720&width=500"
  },
  "favicon": "/favicon.svg",
  "colors": {
    "primary": "#4353FF",
    "light": "#4353FF",
    "dark": "#030416",
    "anchors": {
      "from": "#4353FF",
      "to": "#07C983"
    }
  },
  "topbarLinks": [
    {
      "name": "Support",
      "url": "mailto:hi@mintlify.com"
    }
  ],
  "topbarCtaButton": {
    "name": "Dashboard",
    "url": "https://dashboard.mintlify.com"
  },
  "tabs": [
    {
      "name": "API Reference",
      "url": "api-reference"
    }
  ],
  "anchors": [
    {
      "name": "Documentation",
      "icon": "book-open-cover",
      "url": "https://mintlify.com/docs"
    },
    {
      "name": "Community",
      "icon": "slack",
      "url": "https://mintlify.com/community"
    },
    {
      "name": "Blog",
      "icon": "newspaper",
      "url": "https://mintlify.com/blog"
    }
  ],
  "navigation": [
    {
      "group": "Get Started",
      "pages": [
        "introduction",
        "quickstart",
        "development"
      ]
    },
    {
      "group": "Essentials",
      "pages": [
        "essentials/markdown",
        "essentials/code",
        "essentials/images",
        "essentials/settings",
        "essentials/navigation",
        "essentials/reusable-snippets"
      ]
    },
    {
      "group": "API Documentation",
      "pages": [
        "api-reference/introduction"
      ]
    },
    {
      "group": "Endpoint Examples",
      "pages": [
        "api-reference/endpoint/get",
        "api-reference/endpoint/create",
        "api-reference/endpoint/delete"
      ]
    }
  ],
  "footerSocials": {
    "x": "https://x.com/mintlify",
    "github": "https://github.com/mintlify",
    "linkedin": "https://www.linkedin.com/company/mintsearch" 
  },
  "openapi": ["openapi.json"]
}






